rtl/mac.v
// =============================================================
// Module: mac
// Description: Signed INT8 x INT8 multiply, INT32 accumulate.
//              This is the base compute primitive for the
//              systolic array processing elements.
//
//   acc <= (clear) ? (a*b) : acc + (a*b)     -- on enable
//
// Notes:
//   - `clear` synchronously reloads the accumulator with just the
//     current product (used to start a new output computation
//     without a full module reset).
//   - `rst` is an async reset that zeroes everything.
//   - `en` gates whether accumulation happens this cycle (lets the
//     systolic array stall/hold state cleanly).
// =============================================================

module mac #(
    parameter DATA_WIDTH = 8,
    parameter ACC_WIDTH  = 32
)(
    input  wire                        clk,
    input  wire                        rst,      // async, active-high
    input  wire                        en,       // accumulate enable
    input  wire                        clear,    // sync clear-and-load
    input  wire signed [DATA_WIDTH-1:0] a,
    input  wire signed [DATA_WIDTH-1:0] b,
    output reg  signed [ACC_WIDTH-1:0]  acc
);

    wire signed [2*DATA_WIDTH-1:0] product;
    assign product = a * b;

    always @(posedge clk or posedge rst) begin
        if (rst) begin
            acc <= {ACC_WIDTH{1'b0}};
        end else if (en) begin
            if (clear)
                acc <= {{(ACC_WIDTH-2*DATA_WIDTH){product[2*DATA_WIDTH-1]}}, product};
            else
                acc <= acc + {{(ACC_WIDTH-2*DATA_WIDTH){product[2*DATA_WIDTH-1]}}, product};
        end
        // en == 0: hold current value (no else needed, acc is a reg)
    end

endmodule

tb/tb_mac.sv
// =============================================================
// Testbench: tb_mac
// Verifies:
//   1. Reset zeroes accumulator
//   2. clear+en loads acc with fresh product (not added to old acc)
//   3. Repeated en (no clear) accumulates correctly across cycles
//   4. en=0 holds the accumulator value
//   5. Signed multiplication is correct (negative operands)
// =============================================================

`timescale 1ns/1ps

module tb_mac;

    localparam DATA_WIDTH = 8;
    localparam ACC_WIDTH  = 32;

    reg                         clk;
    reg                         rst;
    reg                         en;
    reg                         clear;
    reg  signed [DATA_WIDTH-1:0] a;
    reg  signed [DATA_WIDTH-1:0] b;
    wire signed [ACC_WIDTH-1:0]  acc;

    integer errors = 0;
    integer test_num = 0;

    mac #(.DATA_WIDTH(DATA_WIDTH), .ACC_WIDTH(ACC_WIDTH)) dut (
        .clk(clk), .rst(rst), .en(en), .clear(clear),
        .a(a), .b(b), .acc(acc)
    );

    // 100MHz clock
    always #5 clk = ~clk;

    task check(input signed [ACC_WIDTH-1:0] expected, input [127:0] name);
        begin
            test_num = test_num + 1;
            if (acc !== expected) begin
                $display("[FAIL] Test %0d (%0s): expected=%0d got=%0d",
                          test_num, name, expected, acc);
                errors = errors + 1;
            end else begin
                $display("[PASS] Test %0d (%0s): acc=%0d", test_num, name, acc);
            end
        end
    endtask

    initial begin
        $dumpfile("tb_mac.vcd");
        $dumpvars(0, tb_mac);

        clk = 0; rst = 1; en = 0; clear = 0; a = 0; b = 0;
        @(negedge clk);
        @(negedge clk);

        // Test 1: reset holds acc at 0
        check(0, "reset");

        // Test 2: release reset, clear+en loads product (3*4=12)
        rst = 0; a = 8'sd3; b = 8'sd4; en = 1; clear = 1;
        @(negedge clk);
        clear = 0;
        check(32'sd12, "clear-load 3*4");

        // Test 3: accumulate again without clear (12 + 3*4 = 24)
        @(negedge clk);
        check(32'sd24, "accumulate +12");

        // Test 4: accumulate negative operand (-5 * 6 = -30) -> 24 - 30 = -6
        a = -8'sd5; b = 8'sd6;
        @(negedge clk);
        check(32'sd24 - 32'sd30, "accumulate negative");

        // Test 5: en=0 holds value even with changing inputs
        en = 0; a = 8'sd127; b = 8'sd127;
        @(negedge clk);
        check(32'sd24 - 32'sd30, "hold on en=0");

        // Test 6: clear reloads fresh product, discarding old acc
        en = 1; clear = 1; a = -8'sd1; b = -8'sd1; // (-1)*(-1)=1
        @(negedge clk);
        clear = 0;
        check(32'sd1, "clear reload after hold");

        // Test 7: max magnitude operands don't overflow ACC_WIDTH=32
        // -128 * 127 = -16256, well within int32 range
        clear = 1; a = -8'sd128; b = 8'sd127;
        @(negedge clk);
        clear = 0;
        check(-32'sd16256, "max magnitude product");

        // Test 8: async reset mid-operation
        @(negedge clk);
        rst = 1;
        @(negedge clk);
        check(0, "async reset mid-op");

        $display("----------------------------------------");
        if (errors == 0)
            $display("ALL %0d TESTS PASSED", test_num);
        else
            $display("%0d/%0d TESTS FAILED", errors, test_num);
        $display("----------------------------------------");

        $finish;
    end

endmodule

tb_mac.vcd
$date
	Thu Jul  2 23:16:19 2026
$end
$version
	Icarus Verilog
$end
$timescale
	1ps
$end
$scope module tb_mac $end
$var wire 32 ! acc [31:0] $end
$var parameter 32 " ACC_WIDTH $end
$var parameter 32 # DATA_WIDTH $end
$var reg 8 $ a [7:0] $end
$var reg 8 % b [7:0] $end
$var reg 1 & clear $end
$var reg 1 ' clk $end
$var reg 1 ( en $end
$var reg 1 ) rst $end
$var integer 32 * errors [31:0] $end
$var integer 32 + test_num [31:0] $end
$scope module dut $end
$var wire 8 , a [7:0] $end
$var wire 8 - b [7:0] $end
$var wire 1 & clear $end
$var wire 1 ' clk $end
$var wire 1 ( en $end
$var wire 1 ) rst $end
$var wire 16 . product [15:0] $end
$var parameter 32 / ACC_WIDTH $end
$var parameter 32 0 DATA_WIDTH $end
$var reg 32 1 acc [31:0] $end
$upscope $end
$scope task check $end
$var reg 32 2 expected [31:0] $end
$var reg 128 3 name [127:0] $end
$upscope $end
$upscope $end
$enddefinitions $end
$comment Show the parameter values. $end
$dumpall
b1000 0
b100000 /
b1000 #
b100000 "
$end
#0
$dumpvars
bx 3
bx 2
b0 1
b0 .
b0 -
b0 ,
b0 +
b0 *
1)
0(
0'
0&
b0 %
b0 $
b0 !
$end
#5000
1'
#10000
0'
#15000
1'
#20000
1&
1(
b1100 .
b100 %
b100 -
b11 $
b11 ,
0)
b1 +
b111001001100101011100110110010101110100 3
b0 2
0'
#25000
b1100 !
b1100 1
1'
#30000
b10 +
b110001101101100011001010110000101110010001011010110110001101111011000010110010000100000001100110010101000110100 3
b1100 2
0&
0'
#35000
b11000 !
b11000 1
1'
#40000
b110 %
b110 -
b1111111111100010 .
b11111011 $
b11111011 ,
b11 +
b110000101100011011000110111010101101101011101010110110001100001011101000110010100100000001010110011000100110010 3
b11000 2
0'
#45000
b11111111111111111111111111111010 !
b11111111111111111111111111111010 1
1'
#50000
b1111111 %
b1111111 -
b11111100000001 .
b1111111 $
b1111111 ,
0(
b100 +
b1110101011011010111010101101100011000010111010001100101001000000110111001100101011001110110000101110100011010010111011001100101 3
b11111111111111111111111111111010 2
0'
#55000
1'
#60000
b11111111 %
b11111111 -
b1 .
b11111111 $
b11111111 ,
1&
1(
b101 +
b11010000110111101101100011001000010000001101111011011100010000001100101011011100011110100110000 3
0'
#65000
b1 !
b1 1
1'
#70000
b1111111 %
b1111111 -
b1100000010000000 .
b10000000 $
b10000000 ,
b110 +
b1100101011011000110111101100001011001000010000001100001011001100111010001100101011100100010000001101000011011110110110001100100 3
b1 2
1&
0'
#75000
b11111111111111111100000010000000 !
b11111111111111111100000010000000 1
1'
#80000
b111 +
b1100001011001110110111001101001011101000111010101100100011001010010000001110000011100100110111101100100011101010110001101110100 3
b11111111111111111100000010000000 2
0&
0'
#85000
b11111111111111111000000100000000 !
b11111111111111111000000100000000 1
1'
#90000
b0 !
b0 1
1)
0'
#95000
1'
#100000
b1000 +
b1111001011011100110001100100000011100100110010101110011011001010111010000100000011011010110100101100100001011010110111101110000 3
b0 2
0'
